g4camp/ActionInitialization.py
g4camp/CustomPhysicsList.py
g4camp/DataBuffer.py
g4camp/DetectorConstruction.py
g4camp/EventAction.py
g4camp/PrimaryGeneratorAction.py
g4camp/RunAction.py
g4camp/StackingAction.py
g4camp/SteppingAction.py
g4camp/UserPhysicsList.py
g4camp/__about__.py
g4camp/__init__.py
g4camp/g4camp.py
g4camp/run_g4camp.py
g4camp/IO/gParticles.py
g4camp/IO/gPhotons.py
g4camp/IO/gQuant.py
g4camp/IO/gTracks.py
g4camp/examples/electrons.mac
g4camp/examples/example_1.py
g4camp/examples/example_2.py
g4camp/examples/example_vis.py
g4camp/examples/muons.mac
g4camp/examples/vis.mac
g4camp-0.1.23.dist-info/METADATA
g4camp-0.1.23.dist-info/WHEEL
g4camp-0.1.23.dist-info/RECORD
